Metadata-Version: 1.0
Name: mlen-kk-distribution
Version: 0.1
Summary: Gaussian, Binomial and General distributions
Home-page: UNKNOWN
Author: Konstantinos Katsinas
Author-email: konstantinoskatsinas@gmail.com
License: UNKNOWN
Platform: UNKNOWN
